mtkruto/__init__.py
mtkruto/_client.py
mtkruto/_type_extensions.py
mtkruto/_utils.py
mtkruto/_utils_test.py
mtkruto/errors.py
mtkruto/filters.py
mtkruto/types.py
mtkruto-0.2.5.dist-info/LICENSE
mtkruto-0.2.5.dist-info/METADATA
mtkruto-0.2.5.dist-info/WHEEL
mtkruto-0.2.5.dist-info/RECORD
